{
    "border": "normal",
    "floating": "auto_off",
    "layout": "splith",
    "percent": null,
    "rect": {
       "height": 147,
       "width": 206,
       "x": 579,
       "y": 408
    },
    "type": "floating_con",
    "nodes": [
        {
            "border": "pixel",
            "current_border_width": 6,
            "floating": "user_on",
            "geometry": {
               "height": 342,
               "width": 510,
               "x": 0,
               "y": 0
            },
            "name": "cava",
            "percent": 1,
            "swallows": [
               {
                "class": "^URxvt$"
               }
            ],
            "type": "con"
        }
    ]
}

{
    "border": "normal",
    "floating": "auto_off",
    "layout": "splith",
    "percent": null,
    "rect": {
       "height": 186,
       "width": 284,
       "x": 540,
       "y": 211
    },
    "type": "floating_con",
    "nodes": [
        {
            "border": "pixel",
            "current_border_width": 6,
            "floating": "user_on",
            "geometry": {
               "height": 342,
               "width": 510,
               "x": 0,
               "y": 0
            },
            "name": "Pearl Kyoudai - Omae to Ore no Enjou Douro",
            "percent": 1,
            "swallows": [
               {
                "class": "^URxvt$"
               }
            ],
            "type": "con"
        }
    ]
}

